dogsheep_beta/__init__.py
dogsheep_beta/cli.py
dogsheep_beta/utils.py
dogsheep_beta/templates/beta.html
dogsheep_beta-0.10.2.dist-info/METADATA
dogsheep_beta-0.10.2.dist-info/WHEEL
dogsheep_beta-0.10.2.dist-info/entry_points.txt
dogsheep_beta-0.10.2.dist-info/top_level.txt
dogsheep_beta-0.10.2.dist-info/RECORD
