Metadata-Version: 2.1
Name: dogsheep-beta
Version: 0.10.2
Summary: Build a search index across content from multiple SQLite database tables and run faceted searches against it using Datasette
Home-page: https://github.com/dogsheep/beta
Author: Simon Willison
License: Apache License, Version 2.0
Project-URL: Issues, https://github.com/dogsheep/beta/issues
Project-URL: CI, https://github.com/dogsheep/beta/actions
Project-URL: Changelog, https://github.com/dogsheep/beta/releases
Platform: UNKNOWN
Requires-Dist: datasette (>=0.50.2)
Requires-Dist: click
Requires-Dist: PyYAML
Requires-Dist: sqlite-utils (>=3.0)
Provides-Extra: test
Requires-Dist: pytest ; extra == 'test'
Requires-Dist: pytest-asyncio ; extra == 'test'
Requires-Dist: httpx ; extra == 'test'
Requires-Dist: beautifulsoup4 ; extra == 'test'
Requires-Dist: html5lib ; extra == 'test'
